{
    "last_update": "2026-07-14 11:01:39",
    "global_strategy": "Quantum_Engine_V15_FullMatrix",
    "assets": {
        "EURUSD=X": {
            "signal_id": "N/A",
            "execution_lock": false,
            "regime": "trending",
            "direction": "flat",
            "entry_zone_min": 1.1396,
            "entry_zone_max": 1.13973,
            "market_state_snapshot": {
                "analysis_price": 1.13947,
                "vwap": 1.14103,
                "rsi": 47.37,
                "atr_pips": 4.8,
                "macro_trend": "sell",
                "market_regime": "trending"
            },
            "expiration_utc": "2026-07-14 13:01:39",
            "target_tp1_pips": 9.7,
            "target_tp2_pips": 14.3,
            "target_sl_pips": 7.2,
            "risk_percent": 1.0,
            "is_crisis": true,
            "vsa_confirmed": false,
            "squeeze_breakout": false,
            "veto": ""
        },
        "GBPUSD=X": {
            "signal_id": "N/A",
            "execution_lock": false,
            "regime": "range",
            "direction": "flat",
            "entry_zone_min": 1.3367,
            "entry_zone_max": 1.33697,
            "market_state_snapshot": {
                "analysis_price": 1.33724,
                "vwap": 1.33077,
                "rsi": 64.37,
                "atr_pips": 5.7,
                "macro_trend": "flat",
                "market_regime": "range"
            },
            "expiration_utc": "2026-07-14 13:01:39",
            "target_tp1_pips": 11.3,
            "target_tp2_pips": 29.3,
            "target_sl_pips": 8.5,
            "risk_percent": 1.0,
            "is_crisis": true,
            "vsa_confirmed": false,
            "squeeze_breakout": false,
            "veto": ""
        },
        "AUDUSD=X": {
            "signal_id": "N/A",
            "execution_lock": false,
            "regime": "trending",
            "direction": "flat",
            "entry_zone_min": 0.69319,
            "entry_zone_max": 0.69343,
            "market_state_snapshot": {
                "analysis_price": 0.6943,
                "vwap": 0.69211,
                "rsi": 52.11,
                "atr_pips": 3.5,
                "macro_trend": "buy",
                "market_regime": "trending"
            },
            "expiration_utc": "2026-07-14 13:01:39",
            "target_tp1_pips": 7.0,
            "target_tp2_pips": 25.9,
            "target_sl_pips": 5.3,
            "risk_percent": 1.0,
            "is_crisis": true,
            "vsa_confirmed": false,
            "squeeze_breakout": false,
            "veto": ""
        },
        "NZDUSD=X": {
            "signal_id": "N/A",
            "execution_lock": false,
            "regime": "trending",
            "direction": "flat",
            "entry_zone_min": 0.57995,
            "entry_zone_max": 0.57995,
            "market_state_snapshot": {
                "analysis_price": 0.57995,
                "vwap": 0.56959,
                "rsi": 53.57,
                "atr_pips": 3.4,
                "macro_trend": "buy",
                "market_regime": "trending"
            },
            "expiration_utc": "2026-07-14 13:01:39",
            "target_tp1_pips": 6.7,
            "target_tp2_pips": 42.7,
            "target_sl_pips": 5.0,
            "risk_percent": 1.0,
            "is_crisis": true,
            "vsa_confirmed": false,
            "squeeze_breakout": false,
            "veto": ""
        },
        "USDCAD=X": {
            "signal_id": "N/A",
            "execution_lock": false,
            "regime": "range",
            "direction": "flat",
            "entry_zone_min": 1.4128,
            "entry_zone_max": 1.41355,
            "market_state_snapshot": {
                "analysis_price": 1.41066,
                "vwap": 1.4191,
                "rsi": 42.67,
                "atr_pips": 11.3,
                "macro_trend": "sell",
                "market_regime": "range"
            },
            "expiration_utc": "2026-07-14 13:01:39",
            "target_tp1_pips": 22.5,
            "target_tp2_pips": 47.9,
            "target_sl_pips": 16.9,
            "risk_percent": 1.0,
            "is_crisis": true,
            "vsa_confirmed": false,
            "squeeze_breakout": false,
            "veto": ""
        },
        "USDCHF=X": {
            "signal_id": "N/A",
            "execution_lock": false,
            "regime": "trending",
            "direction": "flat",
            "entry_zone_min": 0.81281,
            "entry_zone_max": 0.81281,
            "market_state_snapshot": {
                "analysis_price": 0.81281,
                "vwap": 0.80818,
                "rsi": 36.23,
                "atr_pips": 5.7,
                "macro_trend": "buy",
                "market_regime": "trending"
            },
            "expiration_utc": "2026-07-14 13:01:39",
            "target_tp1_pips": 11.3,
            "target_tp2_pips": 23.4,
            "target_sl_pips": 8.5,
            "risk_percent": 1.0,
            "is_crisis": true,
            "vsa_confirmed": false,
            "squeeze_breakout": false,
            "veto": ""
        },
        "USDJPY=X": {
            "signal_id": "N/A",
            "execution_lock": false,
            "regime": "trending",
            "direction": "flat",
            "entry_zone_min": 162.244,
            "entry_zone_max": 162.244,
            "market_state_snapshot": {
                "analysis_price": 162.244,
                "vwap": 161.98412,
                "rsi": 42.44,
                "atr_pips": 7.7,
                "macro_trend": "buy",
                "market_regime": "trending"
            },
            "expiration_utc": "2026-07-14 13:01:39",
            "target_tp1_pips": 15.3,
            "target_tp2_pips": 22.6,
            "target_sl_pips": 11.5,
            "risk_percent": 1.0,
            "is_crisis": true,
            "vsa_confirmed": false,
            "squeeze_breakout": false,
            "veto": ""
        },
        "EURJPY=X": {
            "signal_id": "N/A",
            "execution_lock": false,
            "regime": "range",
            "direction": "flat",
            "entry_zone_min": 185.01199,
            "entry_zone_max": 185.065,
            "market_state_snapshot": {
                "analysis_price": 184.83701,
                "vwap": 184.7727,
                "rsi": 40.7,
                "atr_pips": 8.2,
                "macro_trend": "sell",
                "market_regime": "range"
            },
            "expiration_utc": "2026-07-14 13:01:39",
            "target_tp1_pips": 16.4,
            "target_tp2_pips": 24.5,
            "target_sl_pips": 12.3,
            "risk_percent": 1.0,
            "is_crisis": true,
            "vsa_confirmed": false,
            "squeeze_breakout": false,
            "veto": ""
        },
        "GBPJPY=X": {
            "signal_id": "N/A",
            "execution_lock": false,
            "regime": "range",
            "direction": "flat",
            "entry_zone_min": 216.903,
            "entry_zone_max": 216.961,
            "market_state_snapshot": {
                "analysis_price": 216.97501,
                "vwap": 215.55018,
                "rsi": 62.39,
                "atr_pips": 11.6,
                "macro_trend": "flat",
                "market_regime": "range"
            },
            "expiration_utc": "2026-07-14 13:01:39",
            "target_tp1_pips": 23.2,
            "target_tp2_pips": 31.4,
            "target_sl_pips": 17.4,
            "risk_percent": 1.0,
            "is_crisis": true,
            "vsa_confirmed": false,
            "squeeze_breakout": false,
            "veto": ""
        },
        "AUDJPY=X": {
            "signal_id": "N/A",
            "execution_lock": false,
            "regime": "range",
            "direction": "flat",
            "entry_zone_min": 112.301,
            "entry_zone_max": 112.358,
            "market_state_snapshot": {
                "analysis_price": 112.61,
                "vwap": 112.06648,
                "rsi": 47.31,
                "atr_pips": 6.8,
                "macro_trend": "buy",
                "market_regime": "range"
            },
            "expiration_utc": "2026-07-14 13:01:39",
            "target_tp1_pips": 13.7,
            "target_tp2_pips": 34.1,
            "target_sl_pips": 10.2,
            "risk_percent": 1.0,
            "is_crisis": true,
            "vsa_confirmed": false,
            "squeeze_breakout": false,
            "veto": ""
        },
        "NZDJPY=X": {
            "signal_id": "N/A",
            "execution_lock": false,
            "regime": "trending",
            "direction": "flat",
            "entry_zone_min": 94.055,
            "entry_zone_max": 94.055,
            "market_state_snapshot": {
                "analysis_price": 94.055,
                "vwap": 92.22824,
                "rsi": 48.4,
                "atr_pips": 6.1,
                "macro_trend": "buy",
                "market_regime": "trending"
            },
            "expiration_utc": "2026-07-14 13:01:39",
            "target_tp1_pips": 12.1,
            "target_tp2_pips": 60.0,
            "target_sl_pips": 9.1,
            "risk_percent": 1.0,
            "is_crisis": true,
            "vsa_confirmed": false,
            "squeeze_breakout": false,
            "veto": ""
        },
        "CADJPY=X": {
            "signal_id": "N/A",
            "execution_lock": false,
            "regime": "range",
            "direction": "flat",
            "entry_zone_min": 114.731,
            "entry_zone_max": 114.779,
            "market_state_snapshot": {
                "analysis_price": 115.009,
                "vwap": 114.12736,
                "rsi": 53.12,
                "atr_pips": 7.5,
                "macro_trend": "buy",
                "market_regime": "range"
            },
            "expiration_utc": "2026-07-14 13:01:39",
            "target_tp1_pips": 14.9,
            "target_tp2_pips": 33.8,
            "target_sl_pips": 11.2,
            "risk_percent": 1.0,
            "is_crisis": true,
            "vsa_confirmed": false,
            "squeeze_breakout": false,
            "veto": ""
        },
        "CHFJPY=X": {
            "signal_id": "N/A",
            "execution_lock": false,
            "regime": "trending",
            "direction": "flat",
            "entry_zone_min": 199.605,
            "entry_zone_max": 199.605,
            "market_state_snapshot": {
                "analysis_price": 199.605,
                "vwap": 200.40867,
                "rsi": 66.48,
                "atr_pips": 12.1,
                "macro_trend": "sell",
                "market_regime": "trending"
            },
            "expiration_utc": "2026-07-14 13:01:39",
            "target_tp1_pips": 24.2,
            "target_tp2_pips": 41.1,
            "target_sl_pips": 18.2,
            "risk_percent": 1.0,
            "is_crisis": true,
            "vsa_confirmed": false,
            "squeeze_breakout": false,
            "veto": ""
        },
        "EURGBP=X": {
            "signal_id": "N/A",
            "execution_lock": false,
            "regime": "range",
            "direction": "flat",
            "entry_zone_min": 0.85307,
            "entry_zone_max": 0.85331,
            "market_state_snapshot": {
                "analysis_price": 0.85183,
                "vwap": 0.85718,
                "rsi": 29.34,
                "atr_pips": 3.3,
                "macro_trend": "sell",
                "market_regime": "range"
            },
            "expiration_utc": "2026-07-14 13:01:39",
            "target_tp1_pips": 6.5,
            "target_tp2_pips": 14.8,
            "target_sl_pips": 4.9,
            "risk_percent": 1.0,
            "is_crisis": true,
            "vsa_confirmed": false,
            "squeeze_breakout": false,
            "veto": ""
        },
        "EURAUD=X": {
            "signal_id": "N/A",
            "execution_lock": false,
            "regime": "range",
            "direction": "flat",
            "entry_zone_min": 1.64124,
            "entry_zone_max": 1.64124,
            "market_state_snapshot": {
                "analysis_price": 1.64124,
                "vwap": 1.64854,
                "rsi": 45.02,
                "atr_pips": 11.2,
                "macro_trend": "sell",
                "market_regime": "range"
            },
            "expiration_utc": "2026-07-14 13:01:39",
            "target_tp1_pips": 22.4,
            "target_tp2_pips": 50.5,
            "target_sl_pips": 16.8,
            "risk_percent": 1.0,
            "is_crisis": true,
            "vsa_confirmed": false,
            "squeeze_breakout": false,
            "veto": ""
        },
        "EURNZD=X": {
            "signal_id": "N/A",
            "execution_lock": false,
            "regime": "trending",
            "direction": "flat",
            "entry_zone_min": 1.97412,
            "entry_zone_max": 1.97637,
            "market_state_snapshot": {
                "analysis_price": 1.9649,
                "vwap": 2.00308,
                "rsi": 47.08,
                "atr_pips": 14.5,
                "macro_trend": "sell",
                "market_regime": "trending"
            },
            "expiration_utc": "2026-07-14 13:01:39",
            "target_tp1_pips": 28.9,
            "target_tp2_pips": 128.1,
            "target_sl_pips": 21.7,
            "risk_percent": 1.0,
            "is_crisis": true,
            "vsa_confirmed": false,
            "squeeze_breakout": false,
            "veto": ""
        },
        "EURCAD=X": {
            "signal_id": "N/A",
            "execution_lock": false,
            "regime": "range",
            "direction": "flat",
            "entry_zone_min": 1.60693,
            "entry_zone_max": 1.60693,
            "market_state_snapshot": {
                "analysis_price": 1.60693,
                "vwap": 1.61869,
                "rsi": 40.8,
                "atr_pips": 10.8,
                "macro_trend": "sell",
                "market_regime": "range"
            },
            "expiration_utc": "2026-07-14 13:01:39",
            "target_tp1_pips": 21.6,
            "target_tp2_pips": 42.2,
            "target_sl_pips": 16.2,
            "risk_percent": 1.0,
            "is_crisis": true,
            "vsa_confirmed": false,
            "squeeze_breakout": false,
            "veto": ""
        },
        "EURCHF=X": {
            "signal_id": "N/A",
            "execution_lock": false,
            "regime": "range",
            "direction": "flat",
            "entry_zone_min": 0.92591,
            "entry_zone_max": 0.92591,
            "market_state_snapshot": {
                "analysis_price": 0.92591,
                "vwap": 0.92176,
                "rsi": 16.05,
                "atr_pips": 7.2,
                "macro_trend": "buy",
                "market_regime": "range"
            },
            "expiration_utc": "2026-07-14 13:01:39",
            "target_tp1_pips": 14.5,
            "target_tp2_pips": 19.9,
            "target_sl_pips": 10.8,
            "risk_percent": 1.0,
            "is_crisis": true,
            "vsa_confirmed": false,
            "squeeze_breakout": false,
            "veto": ""
        },
        "GBPAUD=X": {
            "signal_id": "N/A",
            "execution_lock": false,
            "regime": "range",
            "direction": "flat",
            "entry_zone_min": 1.92871,
            "entry_zone_max": 1.92953,
            "market_state_snapshot": {
                "analysis_price": 1.92657,
                "vwap": 1.92318,
                "rsi": 58.94,
                "atr_pips": 11.4,
                "macro_trend": "sell",
                "market_regime": "range"
            },
            "expiration_utc": "2026-07-14 13:01:39",
            "target_tp1_pips": 22.9,
            "target_tp2_pips": 39.6,
            "target_sl_pips": 17.1,
            "risk_percent": 1.0,
            "is_crisis": true,
            "vsa_confirmed": false,
            "squeeze_breakout": true,
            "veto": ""
        },
        "GBPNZD=X": {
            "signal_id": "N/A",
            "execution_lock": false,
            "regime": "trending",
            "direction": "flat",
            "entry_zone_min": 2.31565,
            "entry_zone_max": 2.31767,
            "market_state_snapshot": {
                "analysis_price": 2.30652,
                "vwap": 2.33666,
                "rsi": 56.51,
                "atr_pips": 16.6,
                "macro_trend": "sell",
                "market_regime": "trending"
            },
            "expiration_utc": "2026-07-14 13:01:39",
            "target_tp1_pips": 33.2,
            "target_tp2_pips": 130.8,
            "target_sl_pips": 24.9,
            "risk_percent": 1.0,
            "is_crisis": true,
            "vsa_confirmed": false,
            "squeeze_breakout": false,
            "veto": ""
        },
        "GBPCAD=X": {
            "signal_id": "N/A",
            "execution_lock": false,
            "regime": "range",
            "direction": "flat",
            "entry_zone_min": 1.88838,
            "entry_zone_max": 1.88903,
            "market_state_snapshot": {
                "analysis_price": 1.88624,
                "vwap": 1.88835,
                "rsi": 53.93,
                "atr_pips": 11.3,
                "macro_trend": "sell",
                "market_regime": "range"
            },
            "expiration_utc": "2026-07-14 13:01:39",
            "target_tp1_pips": 22.5,
            "target_tp2_pips": 33.4,
            "target_sl_pips": 16.9,
            "risk_percent": 1.0,
            "is_crisis": true,
            "vsa_confirmed": false,
            "squeeze_breakout": false,
            "veto": ""
        },
        "GBPCHF=X": {
            "signal_id": "N/A",
            "execution_lock": false,
            "regime": "range",
            "direction": "flat",
            "entry_zone_min": 1.08528,
            "entry_zone_max": 1.08611,
            "market_state_snapshot": {
                "analysis_price": 1.08688,
                "vwap": 1.0753,
                "rsi": 43.17,
                "atr_pips": 8.9,
                "macro_trend": "buy",
                "market_regime": "range"
            },
            "expiration_utc": "2026-07-14 13:01:39",
            "target_tp1_pips": 17.8,
            "target_tp2_pips": 16.0,
            "target_sl_pips": 13.4,
            "risk_percent": 1.0,
            "is_crisis": true,
            "vsa_confirmed": false,
            "squeeze_breakout": false,
            "veto": ""
        },
        "AUDCAD=X": {
            "signal_id": "N/A",
            "execution_lock": false,
            "regime": "range",
            "direction": "flat",
            "entry_zone_min": 0.97902,
            "entry_zone_max": 0.97902,
            "market_state_snapshot": {
                "analysis_price": 0.97902,
                "vwap": 0.98155,
                "rsi": 44.83,
                "atr_pips": 13.5,
                "macro_trend": "sell",
                "market_regime": "range"
            },
            "expiration_utc": "2026-07-14 13:01:39",
            "target_tp1_pips": 27.0,
            "target_tp2_pips": 16.5,
            "target_sl_pips": 20.3,
            "risk_percent": 1.0,
            "is_crisis": true,
            "vsa_confirmed": false,
            "squeeze_breakout": true,
            "veto": ""
        },
        "AUDCHF=X": {
            "signal_id": "N/A",
            "execution_lock": false,
            "regime": "range",
            "direction": "flat",
            "entry_zone_min": 0.56257,
            "entry_zone_max": 0.56347,
            "market_state_snapshot": {
                "analysis_price": 0.56409,
                "vwap": 0.5589,
                "rsi": 32.32,
                "atr_pips": 9.4,
                "macro_trend": "buy",
                "market_regime": "range"
            },
            "expiration_utc": "2026-07-14 13:01:39",
            "target_tp1_pips": 18.8,
            "target_tp2_pips": 15.5,
            "target_sl_pips": 14.1,
            "risk_percent": 1.0,
            "is_crisis": true,
            "vsa_confirmed": false,
            "squeeze_breakout": false,
            "veto": ""
        },
        "AUDNZD=X": {
            "signal_id": "N/A",
            "execution_lock": false,
            "regime": "trending",
            "direction": "flat",
            "entry_zone_min": 1.19715,
            "entry_zone_max": 1.19715,
            "market_state_snapshot": {
                "analysis_price": 1.19715,
                "vwap": 1.21483,
                "rsi": 48.48,
                "atr_pips": 8.5,
                "macro_trend": "sell",
                "market_regime": "trending"
            },
            "expiration_utc": "2026-07-14 13:01:39",
            "target_tp1_pips": 17.0,
            "target_tp2_pips": 47.6,
            "target_sl_pips": 12.7,
            "risk_percent": 1.0,
            "is_crisis": true,
            "vsa_confirmed": false,
            "squeeze_breakout": true,
            "veto": ""
        },
        "NZDCAD=X": {
            "signal_id": "N/A",
            "execution_lock": false,
            "regime": "trending",
            "direction": "flat",
            "entry_zone_min": 0.81482,
            "entry_zone_max": 0.81568,
            "market_state_snapshot": {
                "analysis_price": 0.81767,
                "vwap": 0.80796,
                "rsi": 46.25,
                "atr_pips": 6.6,
                "macro_trend": "buy",
                "market_regime": "trending"
            },
            "expiration_utc": "2026-07-14 13:01:39",
            "target_tp1_pips": 13.2,
            "target_tp2_pips": 34.8,
            "target_sl_pips": 9.9,
            "risk_percent": 1.0,
            "is_crisis": true,
            "vsa_confirmed": false,
            "squeeze_breakout": true,
            "veto": ""
        },
        "NZDCHF=X": {
            "signal_id": "N/A",
            "execution_lock": false,
            "regime": "trending",
            "direction": "flat",
            "entry_zone_min": 0.47116,
            "entry_zone_max": 0.47116,
            "market_state_snapshot": {
                "analysis_price": 0.47116,
                "vwap": 0.46006,
                "rsi": 34.33,
                "atr_pips": 4.3,
                "macro_trend": "buy",
                "market_regime": "trending"
            },
            "expiration_utc": "2026-07-14 13:01:39",
            "target_tp1_pips": 8.7,
            "target_tp2_pips": 25.6,
            "target_sl_pips": 6.5,
            "risk_percent": 1.0,
            "is_crisis": true,
            "vsa_confirmed": false,
            "squeeze_breakout": true,
            "veto": ""
        },
        "CADCHF=X": {
            "signal_id": "N/A",
            "execution_lock": false,
            "regime": "range",
            "direction": "flat",
            "entry_zone_min": 0.57481,
            "entry_zone_max": 0.57578,
            "market_state_snapshot": {
                "analysis_price": 0.57616,
                "vwap": 0.5692,
                "rsi": 40.69,
                "atr_pips": 10.0,
                "macro_trend": "buy",
                "market_regime": "range"
            },
            "expiration_utc": "2026-07-14 13:01:39",
            "target_tp1_pips": 20.1,
            "target_tp2_pips": 14.4,
            "target_sl_pips": 15.1,
            "risk_percent": 1.0,
            "is_crisis": true,
            "vsa_confirmed": false,
            "squeeze_breakout": false,
            "veto": ""
        },
        "GC=F": {
            "signal_id": "N/A",
            "execution_lock": false,
            "regime": "trending",
            "direction": "flat",
            "entry_zone_min": 4031.1001,
            "entry_zone_max": 4036.3999,
            "market_state_snapshot": {
                "analysis_price": 4025.8999,
                "vwap": 4086.38253,
                "rsi": 43.98,
                "atr_pips": 64.1,
                "macro_trend": "sell",
                "market_regime": "trending"
            },
            "expiration_utc": "2026-07-14 13:01:39",
            "target_tp1_pips": 128.3,
            "target_tp2_pips": 355.0,
            "target_sl_pips": 96.2,
            "risk_percent": 1.0,
            "is_crisis": true,
            "vsa_confirmed": false,
            "squeeze_breakout": true,
            "veto": ""
        },
        "ETH-USD": {
            "signal_id": "N/A",
            "execution_lock": false,
            "regime": "range",
            "direction": "flat",
            "entry_zone_min": 1798.39001,
            "entry_zone_max": 1798.39001,
            "market_state_snapshot": {
                "analysis_price": 1798.39001,
                "vwap": 1722.96979,
                "rsi": 70.25,
                "atr_pips": 51.9,
                "macro_trend": "buy",
                "market_regime": "range"
            },
            "expiration_utc": "2026-07-14 13:01:39",
            "target_tp1_pips": 103.7,
            "target_tp2_pips": 444.2,
            "target_sl_pips": 77.8,
            "risk_percent": 1.0,
            "is_crisis": true,
            "vsa_confirmed": true,
            "squeeze_breakout": false,
            "veto": ""
        },
        "LTC-USD": {
            "signal_id": "N/A",
            "execution_lock": false,
            "regime": "range",
            "direction": "flat",
            "entry_zone_min": 43.62,
            "entry_zone_max": 43.7,
            "market_state_snapshot": {
                "analysis_price": 43.7,
                "vwap": 43.91327,
                "rsi": 51.32,
                "atr_pips": 9.6,
                "macro_trend": "sell",
                "market_regime": "range"
            },
            "expiration_utc": "2026-07-14 13:01:39",
            "target_tp1_pips": 19.1,
            "target_tp2_pips": 49.0,
            "target_sl_pips": 14.4,
            "risk_percent": 1.0,
            "is_crisis": true,
            "vsa_confirmed": false,
            "squeeze_breakout": true,
            "veto": ""
        },
        "DOGE-USD": {
            "signal_id": "N/A",
            "execution_lock": false,
            "regime": "range",
            "direction": "flat",
            "entry_zone_min": 0.0722,
            "entry_zone_max": 0.0722,
            "market_state_snapshot": {
                "analysis_price": 0.0722,
                "vwap": 0.07414,
                "rsi": 47.54,
                "atr_pips": 1.5,
                "macro_trend": "sell",
                "market_regime": "range"
            },
            "expiration_utc": "2026-07-14 13:01:39",
            "target_tp1_pips": 5.0,
            "target_tp2_pips": 10.5,
            "target_sl_pips": 3.0,
            "risk_percent": 1.0,
            "is_crisis": false,
            "vsa_confirmed": false,
            "squeeze_breakout": true,
            "veto": ""
        }
    }
}