{
    "last_update": "2026-06-23 23:35:57",
    "global_strategy": "Quantum_Engine_V15_FullMatrix",
    "assets": {
        "EURUSD=X": {
            "signal_id": "N/A",
            "execution_lock": false,
            "regime": "range",
            "direction": "flat",
            "entry_zone_min": 1.13843,
            "entry_zone_max": 1.13843,
            "market_state_snapshot": {
                "analysis_price": 1.13843,
                "vwap": 1.15413,
                "rsi": 50.0,
                "atr_pips": 2.4,
                "macro_trend": "sell",
                "market_regime": "range"
            },
            "expiration_utc": "2026-06-24 01:35:57",
            "target_tp1_pips": 5.0,
            "target_tp2_pips": 24.7,
            "target_sl_pips": 3.6,
            "risk_percent": 1.0,
            "is_crisis": true,
            "vsa_confirmed": false,
            "squeeze_breakout": false,
            "veto": ""
        },
        "GBPUSD=X": {
            "signal_id": "N/A",
            "execution_lock": false,
            "regime": "range",
            "direction": "flat",
            "entry_zone_min": 1.32132,
            "entry_zone_max": 1.32188,
            "market_state_snapshot": {
                "analysis_price": 1.31989,
                "vwap": 1.33496,
                "rsi": 55.28,
                "atr_pips": 3.1,
                "macro_trend": "sell",
                "market_regime": "range"
            },
            "expiration_utc": "2026-06-24 01:35:57",
            "target_tp1_pips": 6.3,
            "target_tp2_pips": 25.3,
            "target_sl_pips": 4.7,
            "risk_percent": 1.0,
            "is_crisis": true,
            "vsa_confirmed": false,
            "squeeze_breakout": false,
            "veto": ""
        },
        "AUDUSD=X": {
            "signal_id": "N/A",
            "execution_lock": false,
            "regime": "range",
            "direction": "flat",
            "entry_zone_min": 0.69161,
            "entry_zone_max": 0.69161,
            "market_state_snapshot": {
                "analysis_price": 0.69161,
                "vwap": 0.70435,
                "rsi": 41.38,
                "atr_pips": 1.8,
                "macro_trend": "sell",
                "market_regime": "range"
            },
            "expiration_utc": "2026-06-24 01:35:57",
            "target_tp1_pips": 5.0,
            "target_tp2_pips": 35.1,
            "target_sl_pips": 3.0,
            "risk_percent": 1.0,
            "is_crisis": true,
            "vsa_confirmed": false,
            "squeeze_breakout": true,
            "veto": ""
        },
        "NZDUSD=X": {
            "signal_id": "N/A",
            "execution_lock": false,
            "regime": "range",
            "direction": "flat",
            "entry_zone_min": 0.56667,
            "entry_zone_max": 0.56667,
            "market_state_snapshot": {
                "analysis_price": 0.56667,
                "vwap": 0.58008,
                "rsi": 44.59,
                "atr_pips": 3.0,
                "macro_trend": "sell",
                "market_regime": "range"
            },
            "expiration_utc": "2026-06-24 01:35:57",
            "target_tp1_pips": 6.0,
            "target_tp2_pips": 22.9,
            "target_sl_pips": 4.5,
            "risk_percent": 1.0,
            "is_crisis": true,
            "vsa_confirmed": false,
            "squeeze_breakout": false,
            "veto": ""
        },
        "USDCAD=X": {
            "signal_id": "N/A",
            "execution_lock": false,
            "regime": "range",
            "direction": "flat",
            "entry_zone_min": 1.42115,
            "entry_zone_max": 1.42115,
            "market_state_snapshot": {
                "analysis_price": 1.42115,
                "vwap": 1.40137,
                "rsi": 53.49,
                "atr_pips": 7.1,
                "macro_trend": "buy",
                "market_regime": "range"
            },
            "expiration_utc": "2026-06-24 01:35:57",
            "target_tp1_pips": 14.3,
            "target_tp2_pips": 45.5,
            "target_sl_pips": 10.7,
            "risk_percent": 1.0,
            "is_crisis": true,
            "vsa_confirmed": false,
            "squeeze_breakout": true,
            "veto": ""
        },
        "USDCHF=X": {
            "signal_id": "N/A",
            "execution_lock": false,
            "regime": "range",
            "direction": "flat",
            "entry_zone_min": 0.80963,
            "entry_zone_max": 0.80963,
            "market_state_snapshot": {
                "analysis_price": 0.80963,
                "vwap": 0.79832,
                "rsi": 47.34,
                "atr_pips": 5.4,
                "macro_trend": "buy",
                "market_regime": "range"
            },
            "expiration_utc": "2026-06-24 01:35:57",
            "target_tp1_pips": 10.9,
            "target_tp2_pips": 21.7,
            "target_sl_pips": 8.2,
            "risk_percent": 1.0,
            "is_crisis": true,
            "vsa_confirmed": false,
            "squeeze_breakout": false,
            "veto": ""
        },
        "USDJPY=X": {
            "signal_id": "N/A",
            "execution_lock": false,
            "regime": "range",
            "direction": "flat",
            "entry_zone_min": 161.56599,
            "entry_zone_max": 161.56599,
            "market_state_snapshot": {
                "analysis_price": 161.56599,
                "vwap": 160.54054,
                "rsi": 52.7,
                "atr_pips": 5.6,
                "macro_trend": "buy",
                "market_regime": "range"
            },
            "expiration_utc": "2026-06-24 01:35:57",
            "target_tp1_pips": 11.1,
            "target_tp2_pips": 16.0,
            "target_sl_pips": 8.4,
            "risk_percent": 1.0,
            "is_crisis": true,
            "vsa_confirmed": false,
            "squeeze_breakout": false,
            "veto": ""
        },
        "EURJPY=X": {
            "signal_id": "N/A",
            "execution_lock": false,
            "regime": "range",
            "direction": "flat",
            "entry_zone_min": 184.002,
            "entry_zone_max": 184.10899,
            "market_state_snapshot": {
                "analysis_price": 183.85699,
                "vwap": 185.22447,
                "rsi": 49.22,
                "atr_pips": 7.9,
                "macro_trend": "sell",
                "market_regime": "range"
            },
            "expiration_utc": "2026-06-24 01:35:57",
            "target_tp1_pips": 15.7,
            "target_tp2_pips": 34.2,
            "target_sl_pips": 11.8,
            "risk_percent": 1.0,
            "is_crisis": false,
            "vsa_confirmed": false,
            "squeeze_breakout": false,
            "veto": ""
        },
        "GBPJPY=X": {
            "signal_id": "N/A",
            "execution_lock": false,
            "regime": "range",
            "direction": "flat",
            "entry_zone_min": 213.29601,
            "entry_zone_max": 213.325,
            "market_state_snapshot": {
                "analysis_price": 213.241,
                "vwap": 214.29778,
                "rsi": 52.53,
                "atr_pips": 11.5,
                "macro_trend": "sell",
                "market_regime": "range"
            },
            "expiration_utc": "2026-06-24 01:35:57",
            "target_tp1_pips": 23.1,
            "target_tp2_pips": 32.7,
            "target_sl_pips": 17.3,
            "risk_percent": 1.0,
            "is_crisis": false,
            "vsa_confirmed": false,
            "squeeze_breakout": false,
            "veto": ""
        },
        "AUDJPY=X": {
            "signal_id": "N/A",
            "execution_lock": false,
            "regime": "range",
            "direction": "flat",
            "entry_zone_min": 111.934,
            "entry_zone_max": 111.995,
            "market_state_snapshot": {
                "analysis_price": 111.687,
                "vwap": 113.02891,
                "rsi": 42.9,
                "atr_pips": 7.2,
                "macro_trend": "sell",
                "market_regime": "range"
            },
            "expiration_utc": "2026-06-24 01:35:57",
            "target_tp1_pips": 14.3,
            "target_tp2_pips": 53.5,
            "target_sl_pips": 10.7,
            "risk_percent": 1.0,
            "is_crisis": false,
            "vsa_confirmed": false,
            "squeeze_breakout": true,
            "veto": ""
        },
        "NZDJPY=X": {
            "signal_id": "N/A",
            "execution_lock": false,
            "regime": "range",
            "direction": "flat",
            "entry_zone_min": 91.705,
            "entry_zone_max": 91.764,
            "market_state_snapshot": {
                "analysis_price": 91.497,
                "vwap": 93.08908,
                "rsi": 44.07,
                "atr_pips": 7.6,
                "macro_trend": "sell",
                "market_regime": "range"
            },
            "expiration_utc": "2026-06-24 01:35:57",
            "target_tp1_pips": 15.2,
            "target_tp2_pips": 32.8,
            "target_sl_pips": 11.4,
            "risk_percent": 1.0,
            "is_crisis": false,
            "vsa_confirmed": false,
            "squeeze_breakout": false,
            "veto": ""
        },
        "CADJPY=X": {
            "signal_id": "N/A",
            "execution_lock": false,
            "regime": "range",
            "direction": "flat",
            "entry_zone_min": 113.845,
            "entry_zone_max": 113.98,
            "market_state_snapshot": {
                "analysis_price": 113.668,
                "vwap": 114.54312,
                "rsi": 46.36,
                "atr_pips": 6.0,
                "macro_trend": "sell",
                "market_regime": "range"
            },
            "expiration_utc": "2026-06-24 01:35:57",
            "target_tp1_pips": 12.0,
            "target_tp2_pips": 31.2,
            "target_sl_pips": 9.0,
            "risk_percent": 1.0,
            "is_crisis": true,
            "vsa_confirmed": false,
            "squeeze_breakout": true,
            "veto": ""
        },
        "CHFJPY=X": {
            "signal_id": "N/A",
            "execution_lock": false,
            "regime": "range",
            "direction": "flat",
            "entry_zone_min": 199.504,
            "entry_zone_max": 199.504,
            "market_state_snapshot": {
                "analysis_price": 199.504,
                "vwap": 201.08068,
                "rsi": 49.88,
                "atr_pips": 8.9,
                "macro_trend": "sell",
                "market_regime": "range"
            },
            "expiration_utc": "2026-06-24 01:35:57",
            "target_tp1_pips": 17.9,
            "target_tp2_pips": 47.2,
            "target_sl_pips": 13.4,
            "risk_percent": 1.0,
            "is_crisis": false,
            "vsa_confirmed": false,
            "squeeze_breakout": false,
            "veto": ""
        },
        "EURGBP=X": {
            "signal_id": "N/A",
            "execution_lock": false,
            "regime": "range",
            "direction": "flat",
            "entry_zone_min": 0.86272,
            "entry_zone_max": 0.86305,
            "market_state_snapshot": {
                "analysis_price": 0.86217,
                "vwap": 0.86427,
                "rsi": 46.75,
                "atr_pips": 3.2,
                "macro_trend": "sell",
                "market_regime": "range"
            },
            "expiration_utc": "2026-06-24 01:35:57",
            "target_tp1_pips": 6.4,
            "target_tp2_pips": 10.0,
            "target_sl_pips": 4.8,
            "risk_percent": 1.0,
            "is_crisis": false,
            "vsa_confirmed": false,
            "squeeze_breakout": false,
            "veto": ""
        },
        "EURAUD=X": {
            "signal_id": "N/A",
            "execution_lock": false,
            "regime": "trending",
            "direction": "flat",
            "entry_zone_min": 1.64136,
            "entry_zone_max": 1.64248,
            "market_state_snapshot": {
                "analysis_price": 1.64608,
                "vwap": 1.6385,
                "rsi": 57.03,
                "atr_pips": 9.8,
                "macro_trend": "buy",
                "market_regime": "trending"
            },
            "expiration_utc": "2026-06-24 01:35:57",
            "target_tp1_pips": 19.6,
            "target_tp2_pips": 56.2,
            "target_sl_pips": 14.7,
            "risk_percent": 1.0,
            "is_crisis": false,
            "vsa_confirmed": false,
            "squeeze_breakout": true,
            "veto": ""
        },
        "EURNZD=X": {
            "signal_id": "N/A",
            "execution_lock": false,
            "regime": "range",
            "direction": "flat",
            "entry_zone_min": 2.00331,
            "entry_zone_max": 2.00441,
            "market_state_snapshot": {
                "analysis_price": 2.00906,
                "vwap": 1.98935,
                "rsi": 56.67,
                "atr_pips": 18.0,
                "macro_trend": "buy",
                "market_regime": "range"
            },
            "expiration_utc": "2026-06-24 01:35:57",
            "target_tp1_pips": 36.0,
            "target_tp2_pips": 65.3,
            "target_sl_pips": 27.0,
            "risk_percent": 1.0,
            "is_crisis": false,
            "vsa_confirmed": false,
            "squeeze_breakout": false,
            "veto": ""
        },
        "EURCAD=X": {
            "signal_id": "N/A",
            "execution_lock": false,
            "regime": "range",
            "direction": "flat",
            "entry_zone_min": 1.61721,
            "entry_zone_max": 1.61721,
            "market_state_snapshot": {
                "analysis_price": 1.61721,
                "vwap": 1.61677,
                "rsi": 50.86,
                "atr_pips": 8.5,
                "macro_trend": "sell",
                "market_regime": "range"
            },
            "expiration_utc": "2026-06-24 01:35:57",
            "target_tp1_pips": 17.1,
            "target_tp2_pips": 27.5,
            "target_sl_pips": 12.8,
            "risk_percent": 1.0,
            "is_crisis": true,
            "vsa_confirmed": false,
            "squeeze_breakout": true,
            "veto": ""
        },
        "EURCHF=X": {
            "signal_id": "N/A",
            "execution_lock": false,
            "regime": "trending",
            "direction": "flat",
            "entry_zone_min": 0.9214,
            "entry_zone_max": 0.9214,
            "market_state_snapshot": {
                "analysis_price": 0.9214,
                "vwap": 0.92093,
                "rsi": 46.21,
                "atr_pips": 6.7,
                "macro_trend": "sell",
                "market_regime": "trending"
            },
            "expiration_utc": "2026-06-24 01:35:57",
            "target_tp1_pips": 13.3,
            "target_tp2_pips": 22.7,
            "target_sl_pips": 10.0,
            "risk_percent": 1.0,
            "is_crisis": false,
            "vsa_confirmed": false,
            "squeeze_breakout": true,
            "veto": ""
        },
        "GBPAUD=X": {
            "signal_id": "N/A",
            "execution_lock": false,
            "regime": "range",
            "direction": "flat",
            "entry_zone_min": 1.90913,
            "entry_zone_max": 1.90913,
            "market_state_snapshot": {
                "analysis_price": 1.90913,
                "vwap": 1.89574,
                "rsi": 57.99,
                "atr_pips": 13.2,
                "macro_trend": "buy",
                "market_regime": "range"
            },
            "expiration_utc": "2026-06-24 01:35:57",
            "target_tp1_pips": 26.4,
            "target_tp2_pips": 73.0,
            "target_sl_pips": 19.8,
            "risk_percent": 1.0,
            "is_crisis": false,
            "vsa_confirmed": false,
            "squeeze_breakout": false,
            "veto": ""
        },
        "GBPNZD=X": {
            "signal_id": "N/A",
            "execution_lock": false,
            "regime": "range",
            "direction": "flat",
            "entry_zone_min": 2.33008,
            "entry_zone_max": 2.33008,
            "market_state_snapshot": {
                "analysis_price": 2.33008,
                "vwap": 2.30161,
                "rsi": 58.16,
                "atr_pips": 25.5,
                "macro_trend": "buy",
                "market_regime": "range"
            },
            "expiration_utc": "2026-06-24 01:35:57",
            "target_tp1_pips": 51.0,
            "target_tp2_pips": 105.2,
            "target_sl_pips": 38.3,
            "risk_percent": 1.0,
            "is_crisis": false,
            "vsa_confirmed": false,
            "squeeze_breakout": false,
            "veto": ""
        },
        "GBPCAD=X": {
            "signal_id": "N/A",
            "execution_lock": false,
            "regime": "range",
            "direction": "flat",
            "entry_zone_min": 1.8757,
            "entry_zone_max": 1.8757,
            "market_state_snapshot": {
                "analysis_price": 1.8757,
                "vwap": 1.87059,
                "rsi": 52.57,
                "atr_pips": 12.5,
                "macro_trend": "buy",
                "market_regime": "range"
            },
            "expiration_utc": "2026-06-24 01:35:57",
            "target_tp1_pips": 24.9,
            "target_tp2_pips": 35.2,
            "target_sl_pips": 18.7,
            "risk_percent": 1.0,
            "is_crisis": true,
            "vsa_confirmed": false,
            "squeeze_breakout": false,
            "veto": ""
        },
        "GBPCHF=X": {
            "signal_id": "N/A",
            "execution_lock": false,
            "regime": "range",
            "direction": "flat",
            "entry_zone_min": 1.06864,
            "entry_zone_max": 1.06864,
            "market_state_snapshot": {
                "analysis_price": 1.06864,
                "vwap": 1.06549,
                "rsi": 49.72,
                "atr_pips": 8.6,
                "macro_trend": "flat",
                "market_regime": "range"
            },
            "expiration_utc": "2026-06-24 01:35:57",
            "target_tp1_pips": 17.3,
            "target_tp2_pips": 25.6,
            "target_sl_pips": 13.0,
            "risk_percent": 1.0,
            "is_crisis": false,
            "vsa_confirmed": false,
            "squeeze_breakout": false,
            "veto": ""
        },
        "AUDCAD=X": {
            "signal_id": "N/A",
            "execution_lock": false,
            "regime": "range",
            "direction": "flat",
            "entry_zone_min": 0.98245,
            "entry_zone_max": 0.98245,
            "market_state_snapshot": {
                "analysis_price": 0.98245,
                "vwap": 0.9864,
                "rsi": 46.01,
                "atr_pips": 11.5,
                "macro_trend": "sell",
                "market_regime": "range"
            },
            "expiration_utc": "2026-06-24 01:35:57",
            "target_tp1_pips": 22.9,
            "target_tp2_pips": 31.4,
            "target_sl_pips": 17.2,
            "risk_percent": 1.0,
            "is_crisis": true,
            "vsa_confirmed": false,
            "squeeze_breakout": true,
            "veto": ""
        },
        "AUDCHF=X": {
            "signal_id": "N/A",
            "execution_lock": false,
            "regime": "range",
            "direction": "flat",
            "entry_zone_min": 0.5597,
            "entry_zone_max": 0.5597,
            "market_state_snapshot": {
                "analysis_price": 0.5597,
                "vwap": 0.56182,
                "rsi": 44.0,
                "atr_pips": 8.9,
                "macro_trend": "sell",
                "market_regime": "range"
            },
            "expiration_utc": "2026-06-24 01:35:57",
            "target_tp1_pips": 17.8,
            "target_tp2_pips": 31.0,
            "target_sl_pips": 13.3,
            "risk_percent": 1.0,
            "is_crisis": false,
            "vsa_confirmed": false,
            "squeeze_breakout": false,
            "veto": ""
        },
        "AUDNZD=X": {
            "signal_id": "N/A",
            "execution_lock": false,
            "regime": "range",
            "direction": "flat",
            "entry_zone_min": 1.21963,
            "entry_zone_max": 1.22014,
            "market_state_snapshot": {
                "analysis_price": 1.22044,
                "vwap": 1.21393,
                "rsi": 53.36,
                "atr_pips": 16.2,
                "macro_trend": "flat",
                "market_regime": "range"
            },
            "expiration_utc": "2026-06-24 01:35:57",
            "target_tp1_pips": 32.3,
            "target_tp2_pips": 44.9,
            "target_sl_pips": 24.2,
            "risk_percent": 1.0,
            "is_crisis": false,
            "vsa_confirmed": false,
            "squeeze_breakout": false,
            "veto": ""
        },
        "NZDCAD=X": {
            "signal_id": "N/A",
            "execution_lock": false,
            "regime": "range",
            "direction": "flat",
            "entry_zone_min": 0.80578,
            "entry_zone_max": 0.80636,
            "market_state_snapshot": {
                "analysis_price": 0.80484,
                "vwap": 0.81253,
                "rsi": 41.22,
                "atr_pips": 8.3,
                "macro_trend": "sell",
                "market_regime": "range"
            },
            "expiration_utc": "2026-06-24 01:35:57",
            "target_tp1_pips": 16.6,
            "target_tp2_pips": 20.3,
            "target_sl_pips": 12.5,
            "risk_percent": 1.0,
            "is_crisis": true,
            "vsa_confirmed": false,
            "squeeze_breakout": false,
            "veto": ""
        },
        "NZDCHF=X": {
            "signal_id": "N/A",
            "execution_lock": false,
            "regime": "range",
            "direction": "flat",
            "entry_zone_min": 0.45856,
            "entry_zone_max": 0.45856,
            "market_state_snapshot": {
                "analysis_price": 0.45856,
                "vwap": 0.46281,
                "rsi": 41.97,
                "atr_pips": 13.8,
                "macro_trend": "sell",
                "market_regime": "range"
            },
            "expiration_utc": "2026-06-24 01:35:57",
            "target_tp1_pips": 27.6,
            "target_tp2_pips": 28.5,
            "target_sl_pips": 20.7,
            "risk_percent": 1.0,
            "is_crisis": false,
            "vsa_confirmed": false,
            "squeeze_breakout": true,
            "veto": ""
        },
        "CADCHF=X": {
            "signal_id": "N/A",
            "execution_lock": false,
            "regime": "range",
            "direction": "flat",
            "entry_zone_min": 0.56965,
            "entry_zone_max": 0.56965,
            "market_state_snapshot": {
                "analysis_price": 0.56965,
                "vwap": 0.56937,
                "rsi": 47.34,
                "atr_pips": 8.4,
                "macro_trend": "flat",
                "market_regime": "range"
            },
            "expiration_utc": "2026-06-24 01:35:57",
            "target_tp1_pips": 16.9,
            "target_tp2_pips": 15.6,
            "target_sl_pips": 12.6,
            "risk_percent": 1.0,
            "is_crisis": true,
            "vsa_confirmed": false,
            "squeeze_breakout": false,
            "veto": ""
        },
        "GC=F": {
            "signal_id": "N/A",
            "execution_lock": false,
            "regime": "range",
            "direction": "flat",
            "entry_zone_min": 4150.7998,
            "entry_zone_max": 4163.5,
            "market_state_snapshot": {
                "analysis_price": 4117.0,
                "vwap": 4265.06144,
                "rsi": 25.71,
                "atr_pips": 63.6,
                "macro_trend": "sell",
                "market_regime": "range"
            },
            "expiration_utc": "2026-06-24 01:35:57",
            "target_tp1_pips": 127.1,
            "target_tp2_pips": 465.0,
            "target_sl_pips": 95.4,
            "risk_percent": 1.0,
            "is_crisis": true,
            "vsa_confirmed": false,
            "squeeze_breakout": false,
            "veto": ""
        },
        "ETH-USD": {
            "signal_id": "N/A",
            "execution_lock": false,
            "regime": "trending",
            "direction": "flat",
            "entry_zone_min": 1664.14001,
            "entry_zone_max": 1669.68994,
            "market_state_snapshot": {
                "analysis_price": 1661.91003,
                "vwap": 1710.3395,
                "rsi": 51.94,
                "atr_pips": 37.3,
                "macro_trend": "sell",
                "market_regime": "trending"
            },
            "expiration_utc": "2026-06-24 01:35:57",
            "target_tp1_pips": 74.7,
            "target_tp2_pips": 182.8,
            "target_sl_pips": 56.0,
            "risk_percent": 1.0,
            "is_crisis": true,
            "vsa_confirmed": true,
            "squeeze_breakout": true,
            "veto": ""
        },
        "LTC-USD": {
            "signal_id": "fb61997a94",
            "execution_lock": true,
            "regime": "range",
            "direction": "sell",
            "entry_zone_min": 41.985358238220215,
            "entry_zone_max": 42.09464359283447,
            "market_state_snapshot": {
                "analysis_price": 42.04,
                "vwap": 44.14582,
                "rsi": 63.24,
                "atr_pips": 10.9,
                "macro_trend": "sell",
                "market_regime": "range"
            },
            "expiration_utc": "2026-06-24 01:35:57",
            "target_tp1_pips": 41.0,
            "target_tp2_pips": 136.5,
            "target_sl_pips": 27.3,
            "risk_percent": 0.0,
            "is_crisis": true,
            "vsa_confirmed": true,
            "squeeze_breakout": true,
            "veto": ""
        },
        "DOGE-USD": {
            "signal_id": "N/A",
            "execution_lock": false,
            "regime": "range",
            "direction": "flat",
            "entry_zone_min": 0.07878,
            "entry_zone_max": 0.07878,
            "market_state_snapshot": {
                "analysis_price": 0.07878,
                "vwap": 0.08601,
                "rsi": 62.72,
                "atr_pips": 2.1,
                "macro_trend": "sell",
                "market_regime": "range"
            },
            "expiration_utc": "2026-06-24 01:35:57",
            "target_tp1_pips": 5.0,
            "target_tp2_pips": 13.2,
            "target_sl_pips": 3.1,
            "risk_percent": 1.0,
            "is_crisis": false,
            "vsa_confirmed": false,
            "squeeze_breakout": false,
            "veto": ""
        }
    }
}