{
    "last_update": "2026-06-24 12:05:42",
    "global_strategy": "Quantum_Engine_V15_FullMatrix",
    "assets": {
        "EURUSD=X": {
            "signal_id": "N/A",
            "execution_lock": false,
            "regime": "range",
            "direction": "flat",
            "entry_zone_min": 1.13675,
            "entry_zone_max": 1.13701,
            "market_state_snapshot": {
                "analysis_price": 1.13417,
                "vwap": 1.15346,
                "rsi": 29.63,
                "atr_pips": 5.6,
                "macro_trend": "sell",
                "market_regime": "range"
            },
            "expiration_utc": "2026-06-24 14:05:42",
            "target_tp1_pips": 11.2,
            "target_tp2_pips": 45.2,
            "target_sl_pips": 8.4,
            "risk_percent": 1.0,
            "is_crisis": true,
            "vsa_confirmed": false,
            "squeeze_breakout": false,
            "veto": ""
        },
        "GBPUSD=X": {
            "signal_id": "N/A",
            "execution_lock": false,
            "regime": "range",
            "direction": "flat",
            "entry_zone_min": 1.31917,
            "entry_zone_max": 1.31978,
            "market_state_snapshot": {
                "analysis_price": 1.3161,
                "vwap": 1.33435,
                "rsi": 31.84,
                "atr_pips": 8.5,
                "macro_trend": "sell",
                "market_regime": "range"
            },
            "expiration_utc": "2026-06-24 14:05:42",
            "target_tp1_pips": 16.9,
            "target_tp2_pips": 47.8,
            "target_sl_pips": 12.7,
            "risk_percent": 1.0,
            "is_crisis": true,
            "vsa_confirmed": false,
            "squeeze_breakout": false,
            "veto": ""
        },
        "AUDUSD=X": {
            "signal_id": "N/A",
            "execution_lock": false,
            "regime": "range",
            "direction": "flat",
            "entry_zone_min": 0.69185,
            "entry_zone_max": 0.69209,
            "market_state_snapshot": {
                "analysis_price": 0.68975,
                "vwap": 0.70384,
                "rsi": 46.29,
                "atr_pips": 3.7,
                "macro_trend": "sell",
                "market_regime": "range"
            },
            "expiration_utc": "2026-06-24 14:05:42",
            "target_tp1_pips": 7.3,
            "target_tp2_pips": 26.7,
            "target_sl_pips": 5.5,
            "risk_percent": 1.0,
            "is_crisis": true,
            "vsa_confirmed": false,
            "squeeze_breakout": false,
            "veto": ""
        },
        "NZDUSD=X": {
            "signal_id": "N/A",
            "execution_lock": false,
            "regime": "range",
            "direction": "flat",
            "entry_zone_min": 0.56529,
            "entry_zone_max": 0.56558,
            "market_state_snapshot": {
                "analysis_price": 0.56424,
                "vwap": 0.57953,
                "rsi": 41.45,
                "atr_pips": 3.4,
                "macro_trend": "sell",
                "market_regime": "range"
            },
            "expiration_utc": "2026-06-24 14:05:42",
            "target_tp1_pips": 6.8,
            "target_tp2_pips": 27.8,
            "target_sl_pips": 5.1,
            "risk_percent": 1.0,
            "is_crisis": true,
            "vsa_confirmed": false,
            "squeeze_breakout": false,
            "veto": ""
        },
        "USDCAD=X": {
            "signal_id": "N/A",
            "execution_lock": false,
            "regime": "range",
            "direction": "flat",
            "entry_zone_min": 1.42281,
            "entry_zone_max": 1.42281,
            "market_state_snapshot": {
                "analysis_price": 1.42281,
                "vwap": 1.40214,
                "rsi": 48.41,
                "atr_pips": 9.0,
                "macro_trend": "buy",
                "market_regime": "range"
            },
            "expiration_utc": "2026-06-24 14:05:42",
            "target_tp1_pips": 17.9,
            "target_tp2_pips": 26.1,
            "target_sl_pips": 13.4,
            "risk_percent": 1.0,
            "is_crisis": true,
            "vsa_confirmed": false,
            "squeeze_breakout": true,
            "veto": ""
        },
        "USDCHF=X": {
            "signal_id": "N/A",
            "execution_lock": false,
            "regime": "range",
            "direction": "flat",
            "entry_zone_min": 0.81008,
            "entry_zone_max": 0.81042,
            "market_state_snapshot": {
                "analysis_price": 0.81251,
                "vwap": 0.79879,
                "rsi": 66.45,
                "atr_pips": 6.2,
                "macro_trend": "buy",
                "market_regime": "range"
            },
            "expiration_utc": "2026-06-24 14:05:42",
            "target_tp1_pips": 12.3,
            "target_tp2_pips": 32.0,
            "target_sl_pips": 9.2,
            "risk_percent": 1.0,
            "is_crisis": true,
            "vsa_confirmed": false,
            "squeeze_breakout": false,
            "veto": ""
        },
        "USDJPY=X": {
            "signal_id": "3e2af1fd63",
            "execution_lock": true,
            "regime": "range",
            "direction": "buy",
            "entry_zone_min": 161.6291046142578,
            "entry_zone_max": 161.68089294433594,
            "market_state_snapshot": {
                "analysis_price": 161.655,
                "vwap": 160.58171,
                "rsi": 40.69,
                "atr_pips": 5.2,
                "macro_trend": "buy",
                "market_regime": "range"
            },
            "expiration_utc": "2026-06-24 14:05:42",
            "target_tp1_pips": 19.4,
            "target_tp2_pips": 64.5,
            "target_sl_pips": 12.9,
            "risk_percent": 3.0,
            "is_crisis": true,
            "vsa_confirmed": false,
            "squeeze_breakout": false,
            "veto": ""
        },
        "EURJPY=X": {
            "signal_id": "N/A",
            "execution_lock": false,
            "regime": "range",
            "direction": "flat",
            "entry_zone_min": 183.825,
            "entry_zone_max": 183.87801,
            "market_state_snapshot": {
                "analysis_price": 183.31799,
                "vwap": 185.16474,
                "rsi": 24.5,
                "atr_pips": 10.0,
                "macro_trend": "sell",
                "market_regime": "range"
            },
            "expiration_utc": "2026-06-24 14:05:42",
            "target_tp1_pips": 20.0,
            "target_tp2_pips": 60.9,
            "target_sl_pips": 15.0,
            "risk_percent": 1.0,
            "is_crisis": false,
            "vsa_confirmed": false,
            "squeeze_breakout": false,
            "veto": ""
        },
        "GBPJPY=X": {
            "signal_id": "N/A",
            "execution_lock": false,
            "regime": "range",
            "direction": "flat",
            "entry_zone_min": 213.243,
            "entry_zone_max": 213.384,
            "market_state_snapshot": {
                "analysis_price": 212.77299,
                "vwap": 214.25512,
                "rsi": 26.86,
                "atr_pips": 15.9,
                "macro_trend": "sell",
                "market_regime": "range"
            },
            "expiration_utc": "2026-06-24 14:05:42",
            "target_tp1_pips": 31.8,
            "target_tp2_pips": 72.6,
            "target_sl_pips": 23.8,
            "risk_percent": 1.0,
            "is_crisis": false,
            "vsa_confirmed": false,
            "squeeze_breakout": false,
            "veto": ""
        },
        "AUDJPY=X": {
            "signal_id": "N/A",
            "execution_lock": false,
            "regime": "range",
            "direction": "flat",
            "entry_zone_min": 111.602,
            "entry_zone_max": 111.667,
            "market_state_snapshot": {
                "analysis_price": 111.475,
                "vwap": 112.9754,
                "rsi": 42.59,
                "atr_pips": 7.3,
                "macro_trend": "sell",
                "market_regime": "range"
            },
            "expiration_utc": "2026-06-24 14:05:42",
            "target_tp1_pips": 14.7,
            "target_tp2_pips": 38.3,
            "target_sl_pips": 11.0,
            "risk_percent": 1.0,
            "is_crisis": false,
            "vsa_confirmed": false,
            "squeeze_breakout": false,
            "veto": ""
        },
        "NZDJPY=X": {
            "signal_id": "N/A",
            "execution_lock": false,
            "regime": "range",
            "direction": "flat",
            "entry_zone_min": 91.361,
            "entry_zone_max": 91.414,
            "market_state_snapshot": {
                "analysis_price": 91.19,
                "vwap": 93.02378,
                "rsi": 37.81,
                "atr_pips": 7.2,
                "macro_trend": "sell",
                "market_regime": "range"
            },
            "expiration_utc": "2026-06-24 14:05:42",
            "target_tp1_pips": 14.4,
            "target_tp2_pips": 42.0,
            "target_sl_pips": 10.8,
            "risk_percent": 1.0,
            "is_crisis": false,
            "vsa_confirmed": false,
            "squeeze_breakout": false,
            "veto": ""
        },
        "CADJPY=X": {
            "signal_id": "N/A",
            "execution_lock": false,
            "regime": "range",
            "direction": "flat",
            "entry_zone_min": 113.613,
            "entry_zone_max": 113.613,
            "market_state_snapshot": {
                "analysis_price": 113.613,
                "vwap": 114.50982,
                "rsi": 47.4,
                "atr_pips": 5.8,
                "macro_trend": "sell",
                "market_regime": "range"
            },
            "expiration_utc": "2026-06-24 14:05:42",
            "target_tp1_pips": 11.7,
            "target_tp2_pips": 14.3,
            "target_sl_pips": 8.7,
            "risk_percent": 1.0,
            "is_crisis": true,
            "vsa_confirmed": false,
            "squeeze_breakout": false,
            "veto": ""
        },
        "CHFJPY=X": {
            "signal_id": "N/A",
            "execution_lock": false,
            "regime": "range",
            "direction": "flat",
            "entry_zone_min": 199.314,
            "entry_zone_max": 199.414,
            "market_state_snapshot": {
                "analysis_price": 198.923,
                "vwap": 201.01289,
                "rsi": 29.85,
                "atr_pips": 14.4,
                "macro_trend": "sell",
                "market_regime": "range"
            },
            "expiration_utc": "2026-06-24 14:05:42",
            "target_tp1_pips": 28.8,
            "target_tp2_pips": 68.9,
            "target_sl_pips": 21.6,
            "risk_percent": 1.0,
            "is_crisis": false,
            "vsa_confirmed": false,
            "squeeze_breakout": false,
            "veto": ""
        },
        "EURGBP=X": {
            "signal_id": "N/A",
            "execution_lock": false,
            "regime": "range",
            "direction": "flat",
            "entry_zone_min": 0.86164,
            "entry_zone_max": 0.86182,
            "market_state_snapshot": {
                "analysis_price": 0.86152,
                "vwap": 0.86417,
                "rsi": 61.27,
                "atr_pips": 4.2,
                "macro_trend": "sell",
                "market_regime": "range"
            },
            "expiration_utc": "2026-06-24 14:05:42",
            "target_tp1_pips": 8.3,
            "target_tp2_pips": 12.8,
            "target_sl_pips": 6.3,
            "risk_percent": 1.0,
            "is_crisis": false,
            "vsa_confirmed": false,
            "squeeze_breakout": false,
            "veto": ""
        },
        "EURAUD=X": {
            "signal_id": "N/A",
            "execution_lock": false,
            "regime": "range",
            "direction": "flat",
            "entry_zone_min": 1.64441,
            "entry_zone_max": 1.64441,
            "market_state_snapshot": {
                "analysis_price": 1.64441,
                "vwap": 1.63875,
                "rsi": 36.91,
                "atr_pips": 11.1,
                "macro_trend": "buy",
                "market_regime": "range"
            },
            "expiration_utc": "2026-06-24 14:05:42",
            "target_tp1_pips": 22.3,
            "target_tp2_pips": 28.9,
            "target_sl_pips": 16.7,
            "risk_percent": 1.0,
            "is_crisis": false,
            "vsa_confirmed": false,
            "squeeze_breakout": false,
            "veto": ""
        },
        "EURNZD=X": {
            "signal_id": "N/A",
            "execution_lock": false,
            "regime": "range",
            "direction": "flat",
            "entry_zone_min": 2.00812,
            "entry_zone_max": 2.00919,
            "market_state_snapshot": {
                "analysis_price": 2.01008,
                "vwap": 1.99012,
                "rsi": 46.11,
                "atr_pips": 13.6,
                "macro_trend": "buy",
                "market_regime": "range"
            },
            "expiration_utc": "2026-06-24 14:05:42",
            "target_tp1_pips": 27.2,
            "target_tp2_pips": 40.7,
            "target_sl_pips": 20.4,
            "risk_percent": 1.0,
            "is_crisis": false,
            "vsa_confirmed": false,
            "squeeze_breakout": false,
            "veto": ""
        },
        "EURCAD=X": {
            "signal_id": "N/A",
            "execution_lock": false,
            "regime": "range",
            "direction": "flat",
            "entry_zone_min": 1.61587,
            "entry_zone_max": 1.61665,
            "market_state_snapshot": {
                "analysis_price": 1.61343,
                "vwap": 1.61672,
                "rsi": 25.61,
                "atr_pips": 9.9,
                "macro_trend": "sell",
                "market_regime": "range"
            },
            "expiration_utc": "2026-06-24 14:05:42",
            "target_tp1_pips": 19.8,
            "target_tp2_pips": 40.3,
            "target_sl_pips": 14.8,
            "risk_percent": 1.0,
            "is_crisis": true,
            "vsa_confirmed": false,
            "squeeze_breakout": false,
            "veto": ""
        },
        "EURCHF=X": {
            "signal_id": "N/A",
            "execution_lock": false,
            "regime": "range",
            "direction": "flat",
            "entry_zone_min": 0.9214,
            "entry_zone_max": 0.9214,
            "market_state_snapshot": {
                "analysis_price": 0.9214,
                "vwap": 0.92094,
                "rsi": 51.87,
                "atr_pips": 7.8,
                "macro_trend": "sell",
                "market_regime": "range"
            },
            "expiration_utc": "2026-06-24 14:05:42",
            "target_tp1_pips": 15.6,
            "target_tp2_pips": 11.0,
            "target_sl_pips": 11.7,
            "risk_percent": 1.0,
            "is_crisis": false,
            "vsa_confirmed": false,
            "squeeze_breakout": true,
            "veto": ""
        },
        "GBPAUD=X": {
            "signal_id": "N/A",
            "execution_lock": false,
            "regime": "range",
            "direction": "flat",
            "entry_zone_min": 1.90864,
            "entry_zone_max": 1.90965,
            "market_state_snapshot": {
                "analysis_price": 1.90862,
                "vwap": 1.89627,
                "rsi": 29.52,
                "atr_pips": 12.6,
                "macro_trend": "buy",
                "market_regime": "range"
            },
            "expiration_utc": "2026-06-24 14:05:42",
            "target_tp1_pips": 25.2,
            "target_tp2_pips": 53.0,
            "target_sl_pips": 18.9,
            "risk_percent": 1.0,
            "is_crisis": false,
            "vsa_confirmed": false,
            "squeeze_breakout": false,
            "veto": ""
        },
        "GBPNZD=X": {
            "signal_id": "N/A",
            "execution_lock": false,
            "regime": "range",
            "direction": "flat",
            "entry_zone_min": 2.32764,
            "entry_zone_max": 2.33021,
            "market_state_snapshot": {
                "analysis_price": 2.33299,
                "vwap": 2.30279,
                "rsi": 31.48,
                "atr_pips": 15.8,
                "macro_trend": "buy",
                "market_regime": "range"
            },
            "expiration_utc": "2026-06-24 14:05:42",
            "target_tp1_pips": 31.6,
            "target_tp2_pips": 53.5,
            "target_sl_pips": 23.7,
            "risk_percent": 1.0,
            "is_crisis": false,
            "vsa_confirmed": false,
            "squeeze_breakout": false,
            "veto": ""
        },
        "GBPCAD=X": {
            "signal_id": "N/A",
            "execution_lock": false,
            "regime": "range",
            "direction": "flat",
            "entry_zone_min": 1.87271,
            "entry_zone_max": 1.87271,
            "market_state_snapshot": {
                "analysis_price": 1.87271,
                "vwap": 1.87076,
                "rsi": 25.9,
                "atr_pips": 12.6,
                "macro_trend": "sell",
                "market_regime": "range"
            },
            "expiration_utc": "2026-06-24 14:05:42",
            "target_tp1_pips": 25.2,
            "target_tp2_pips": 49.1,
            "target_sl_pips": 18.9,
            "risk_percent": 1.0,
            "is_crisis": true,
            "vsa_confirmed": false,
            "squeeze_breakout": false,
            "veto": ""
        },
        "GBPCHF=X": {
            "signal_id": "N/A",
            "execution_lock": false,
            "regime": "range",
            "direction": "flat",
            "entry_zone_min": 1.06848,
            "entry_zone_max": 1.06916,
            "market_state_snapshot": {
                "analysis_price": 1.06942,
                "vwap": 1.06564,
                "rsi": 43.02,
                "atr_pips": 9.6,
                "macro_trend": "buy",
                "market_regime": "range"
            },
            "expiration_utc": "2026-06-24 14:05:42",
            "target_tp1_pips": 19.2,
            "target_tp2_pips": 16.1,
            "target_sl_pips": 14.4,
            "risk_percent": 1.0,
            "is_crisis": false,
            "vsa_confirmed": false,
            "squeeze_breakout": false,
            "veto": ""
        },
        "AUDCAD=X": {
            "signal_id": "N/A",
            "execution_lock": false,
            "regime": "range",
            "direction": "flat",
            "entry_zone_min": 0.9811,
            "entry_zone_max": 0.9811,
            "market_state_snapshot": {
                "analysis_price": 0.9811,
                "vwap": 0.98622,
                "rsi": 43.99,
                "atr_pips": 13.1,
                "macro_trend": "sell",
                "market_regime": "range"
            },
            "expiration_utc": "2026-06-24 14:05:42",
            "target_tp1_pips": 26.1,
            "target_tp2_pips": 25.4,
            "target_sl_pips": 19.6,
            "risk_percent": 1.0,
            "is_crisis": true,
            "vsa_confirmed": false,
            "squeeze_breakout": false,
            "veto": ""
        },
        "AUDCHF=X": {
            "signal_id": "N/A",
            "execution_lock": false,
            "regime": "range",
            "direction": "flat",
            "entry_zone_min": 0.56029,
            "entry_zone_max": 0.56029,
            "market_state_snapshot": {
                "analysis_price": 0.56029,
                "vwap": 0.56174,
                "rsi": 65.62,
                "atr_pips": 9.7,
                "macro_trend": "sell",
                "market_regime": "range"
            },
            "expiration_utc": "2026-06-24 14:05:42",
            "target_tp1_pips": 19.4,
            "target_tp2_pips": 16.5,
            "target_sl_pips": 14.5,
            "risk_percent": 1.0,
            "is_crisis": false,
            "vsa_confirmed": false,
            "squeeze_breakout": false,
            "veto": ""
        },
        "AUDNZD=X": {
            "signal_id": "N/A",
            "execution_lock": false,
            "regime": "range",
            "direction": "flat",
            "entry_zone_min": 1.22013,
            "entry_zone_max": 1.22117,
            "market_state_snapshot": {
                "analysis_price": 1.22234,
                "vwap": 1.21421,
                "rsi": 61.32,
                "atr_pips": 8.0,
                "macro_trend": "buy",
                "market_regime": "range"
            },
            "expiration_utc": "2026-06-24 14:05:42",
            "target_tp1_pips": 16.0,
            "target_tp2_pips": 24.3,
            "target_sl_pips": 12.0,
            "risk_percent": 1.0,
            "is_crisis": false,
            "vsa_confirmed": false,
            "squeeze_breakout": false,
            "veto": ""
        },
        "NZDCAD=X": {
            "signal_id": "N/A",
            "execution_lock": false,
            "regime": "range",
            "direction": "flat",
            "entry_zone_min": 0.80363,
            "entry_zone_max": 0.80423,
            "market_state_snapshot": {
                "analysis_price": 0.80257,
                "vwap": 0.8122,
                "rsi": 38.81,
                "atr_pips": 5.5,
                "macro_trend": "sell",
                "market_regime": "range"
            },
            "expiration_utc": "2026-06-24 14:05:42",
            "target_tp1_pips": 11.0,
            "target_tp2_pips": 30.1,
            "target_sl_pips": 8.2,
            "risk_percent": 1.0,
            "is_crisis": true,
            "vsa_confirmed": false,
            "squeeze_breakout": false,
            "veto": ""
        },
        "NZDCHF=X": {
            "signal_id": "N/A",
            "execution_lock": false,
            "regime": "range",
            "direction": "flat",
            "entry_zone_min": 0.45836,
            "entry_zone_max": 0.45836,
            "market_state_snapshot": {
                "analysis_price": 0.45836,
                "vwap": 0.46264,
                "rsi": 56.74,
                "atr_pips": 4.4,
                "macro_trend": "sell",
                "market_regime": "range"
            },
            "expiration_utc": "2026-06-24 14:05:42",
            "target_tp1_pips": 8.7,
            "target_tp2_pips": 10.0,
            "target_sl_pips": 6.5,
            "risk_percent": 1.0,
            "is_crisis": false,
            "vsa_confirmed": false,
            "squeeze_breakout": false,
            "veto": ""
        },
        "CADCHF=X": {
            "signal_id": "N/A",
            "execution_lock": false,
            "regime": "range",
            "direction": "flat",
            "entry_zone_min": 0.57106,
            "entry_zone_max": 0.57106,
            "market_state_snapshot": {
                "analysis_price": 0.57106,
                "vwap": 0.5694,
                "rsi": 70.73,
                "atr_pips": 10.2,
                "macro_trend": "buy",
                "market_regime": "range"
            },
            "expiration_utc": "2026-06-24 14:05:42",
            "target_tp1_pips": 20.4,
            "target_tp2_pips": 21.1,
            "target_sl_pips": 15.3,
            "risk_percent": 1.0,
            "is_crisis": true,
            "vsa_confirmed": false,
            "squeeze_breakout": false,
            "veto": ""
        },
        "GC=F": {
            "signal_id": "N/A",
            "execution_lock": false,
            "regime": "range",
            "direction": "flat",
            "entry_zone_min": 4062.3999,
            "entry_zone_max": 4062.3999,
            "market_state_snapshot": {
                "analysis_price": 4062.3999,
                "vwap": 4245.48047,
                "rsi": 25.93,
                "atr_pips": 88.6,
                "macro_trend": "sell",
                "market_regime": "range"
            },
            "expiration_utc": "2026-06-24 14:05:42",
            "target_tp1_pips": 177.1,
            "target_tp2_pips": 917.0,
            "target_sl_pips": 132.9,
            "risk_percent": 1.0,
            "is_crisis": true,
            "vsa_confirmed": false,
            "squeeze_breakout": false,
            "veto": ""
        },
        "ETH-USD": {
            "signal_id": "N/A",
            "execution_lock": false,
            "regime": "range",
            "direction": "flat",
            "entry_zone_min": 1676.88,
            "entry_zone_max": 1676.88,
            "market_state_snapshot": {
                "analysis_price": 1676.88,
                "vwap": 1712.80807,
                "rsi": 59.61,
                "atr_pips": 57.0,
                "macro_trend": "sell",
                "market_regime": "range"
            },
            "expiration_utc": "2026-06-24 14:05:42",
            "target_tp1_pips": 114.0,
            "target_tp2_pips": 233.1,
            "target_sl_pips": 85.5,
            "risk_percent": 1.0,
            "is_crisis": true,
            "vsa_confirmed": false,
            "squeeze_breakout": false,
            "veto": ""
        },
        "LTC-USD": {
            "signal_id": "N/A",
            "execution_lock": false,
            "regime": "range",
            "direction": "flat",
            "entry_zone_min": 42.02,
            "entry_zone_max": 42.08,
            "market_state_snapshot": {
                "analysis_price": 42.16,
                "vwap": 44.19393,
                "rsi": 58.43,
                "atr_pips": 12.5,
                "macro_trend": "sell",
                "market_regime": "range"
            },
            "expiration_utc": "2026-06-24 14:05:42",
            "target_tp1_pips": 25.0,
            "target_tp2_pips": 71.0,
            "target_sl_pips": 18.8,
            "risk_percent": 1.0,
            "is_crisis": true,
            "vsa_confirmed": true,
            "squeeze_breakout": false,
            "veto": ""
        },
        "DOGE-USD": {
            "signal_id": "N/A",
            "execution_lock": false,
            "regime": "range",
            "direction": "flat",
            "entry_zone_min": 0.07915,
            "entry_zone_max": 0.07936,
            "market_state_snapshot": {
                "analysis_price": 0.07892,
                "vwap": 0.0859,
                "rsi": 49.61,
                "atr_pips": 3.0,
                "macro_trend": "sell",
                "market_regime": "range"
            },
            "expiration_utc": "2026-06-24 14:05:42",
            "target_tp1_pips": 6.1,
            "target_tp2_pips": 10.0,
            "target_sl_pips": 4.5,
            "risk_percent": 1.0,
            "is_crisis": false,
            "vsa_confirmed": true,
            "squeeze_breakout": false,
            "veto": ""
        }
    }
}