{
    "last_update": "2026-06-10 11:36:33",
    "global_strategy": "Quantum_Engine_V12",
    "session_active": true,
    "assets": {
        "EURUSD=X": {
            "regime": "range",
            "direction": "flat",
            "entry_zone_min": 1.1546,
            "entry_zone_max": 1.1546,
            "market_state_snapshot": {
                "analysis_price": 1.1546,
                "vwap": 1.16145,
                "rsi": 30.02,
                "atr_pips": 4.2,
                "macro_trend": "sell",
                "market_regime": "range"
            },
            "expiration_utc": "2026-06-10 13:36:33",
            "target_tp1_pips": 10.0,
            "target_tp2_pips": 20.0,
            "target_sl_pips": 6.3,
            "risk_percent": 1.0,
            "is_crisis": true,
            "vsa_confirmed": false,
            "veto": ""
        },
        "GBPUSD=X": {
            "regime": "range",
            "direction": "flat",
            "entry_zone_min": 1.33951,
            "entry_zone_max": 1.33991,
            "market_state_snapshot": {
                "analysis_price": 1.33851,
                "vwap": 1.34302,
                "rsi": 43.93,
                "atr_pips": 5.7,
                "macro_trend": "flat",
                "market_regime": "range"
            },
            "expiration_utc": "2026-06-10 13:36:33",
            "target_tp1_pips": 11.4,
            "target_tp2_pips": 20.0,
            "target_sl_pips": 8.5,
            "risk_percent": 1.0,
            "is_crisis": true,
            "vsa_confirmed": false,
            "veto": ""
        },
        "AUDUSD=X": {
            "regime": "range",
            "direction": "flat",
            "entry_zone_min": 0.70057,
            "entry_zone_max": 0.70057,
            "market_state_snapshot": {
                "analysis_price": 0.70057,
                "vwap": 0.71332,
                "rsi": 31.17,
                "atr_pips": 4.2,
                "macro_trend": "sell",
                "market_regime": "range"
            },
            "expiration_utc": "2026-06-10 13:36:33",
            "target_tp1_pips": 10.0,
            "target_tp2_pips": 27.6,
            "target_sl_pips": 6.4,
            "risk_percent": 1.0,
            "is_crisis": true,
            "vsa_confirmed": false,
            "veto": ""
        },
        "USDCAD=X": {
            "regime": "trending",
            "direction": "flat",
            "entry_zone_min": 1.3927,
            "entry_zone_max": 1.3927,
            "market_state_snapshot": {
                "analysis_price": 1.3927,
                "vwap": 1.38494,
                "rsi": 36.7,
                "atr_pips": 9.1,
                "macro_trend": "flat",
                "market_regime": "trending"
            },
            "expiration_utc": "2026-06-10 13:36:33",
            "target_tp1_pips": 18.1,
            "target_tp2_pips": 30.0,
            "target_sl_pips": 13.6,
            "risk_percent": 1.0,
            "is_crisis": true,
            "vsa_confirmed": false,
            "veto": ""
        },
        "USDJPY=X": {
            "regime": "range",
            "direction": "flat",
            "entry_zone_min": 160.479,
            "entry_zone_max": 160.479,
            "market_state_snapshot": {
                "analysis_price": 160.479,
                "vwap": 159.59097,
                "rsi": 83.82,
                "atr_pips": 3.9,
                "macro_trend": "buy",
                "market_regime": "range"
            },
            "expiration_utc": "2026-06-10 13:36:33",
            "target_tp1_pips": 10.0,
            "target_tp2_pips": 25.4,
            "target_sl_pips": 5.8,
            "risk_percent": 1.0,
            "is_crisis": true,
            "vsa_confirmed": false,
            "veto": ""
        },
        "EURJPY=X": {
            "regime": "range",
            "direction": "flat",
            "entry_zone_min": 185.397,
            "entry_zone_max": 185.44901,
            "market_state_snapshot": {
                "analysis_price": 185.248,
                "vwap": 185.2988,
                "rsi": 45.05,
                "atr_pips": 8.6,
                "macro_trend": "flat",
                "market_regime": "range"
            },
            "expiration_utc": "2026-06-10 13:36:33",
            "target_tp1_pips": 17.2,
            "target_tp2_pips": 30.0,
            "target_sl_pips": 12.9,
            "risk_percent": 1.0,
            "is_crisis": true,
            "vsa_confirmed": false,
            "veto": ""
        },
        "GBPAUD=X": {
            "regime": "range",
            "direction": "flat",
            "entry_zone_min": 1.90506,
            "entry_zone_max": 1.90562,
            "market_state_snapshot": {
                "analysis_price": 1.91093,
                "vwap": 1.88325,
                "rsi": 70.84,
                "atr_pips": 12.5,
                "macro_trend": "buy",
                "market_regime": "range"
            },
            "expiration_utc": "2026-06-10 13:36:33",
            "target_tp1_pips": 25.1,
            "target_tp2_pips": 87.2,
            "target_sl_pips": 18.8,
            "risk_percent": 1.0,
            "is_crisis": true,
            "vsa_confirmed": false,
            "veto": ""
        },
        "EURGBP=X": {
            "regime": "range",
            "direction": "flat",
            "entry_zone_min": 0.86302,
            "entry_zone_max": 0.8633,
            "market_state_snapshot": {
                "analysis_price": 0.86237,
                "vwap": 0.86453,
                "rsi": 39.51,
                "atr_pips": 3.0,
                "macro_trend": "sell",
                "market_regime": "range"
            },
            "expiration_utc": "2026-06-10 13:36:33",
            "target_tp1_pips": 10.0,
            "target_tp2_pips": 20.0,
            "target_sl_pips": 5.0,
            "risk_percent": 1.0,
            "is_crisis": true,
            "vsa_confirmed": false,
            "veto": ""
        },
        "AUDNZD=X": {
            "regime": "range",
            "direction": "flat",
            "entry_zone_min": 1.20621,
            "entry_zone_max": 1.20621,
            "market_state_snapshot": {
                "analysis_price": 1.20621,
                "vwap": 1.21292,
                "rsi": 37.66,
                "atr_pips": 8.1,
                "macro_trend": "sell",
                "market_regime": "range"
            },
            "expiration_utc": "2026-06-10 13:36:33",
            "target_tp1_pips": 16.3,
            "target_tp2_pips": 31.8,
            "target_sl_pips": 12.2,
            "risk_percent": 1.0,
            "is_crisis": true,
            "vsa_confirmed": false,
            "veto": ""
        },
        "CHFJPY=X": {
            "regime": "range",
            "direction": "flat",
            "entry_zone_min": 200.89301,
            "entry_zone_max": 200.89301,
            "market_state_snapshot": {
                "analysis_price": 200.89301,
                "vwap": 202.4136,
                "rsi": 51.72,
                "atr_pips": 13.1,
                "macro_trend": "sell",
                "market_regime": "range"
            },
            "expiration_utc": "2026-06-10 13:36:33",
            "target_tp1_pips": 26.2,
            "target_tp2_pips": 35.3,
            "target_sl_pips": 19.7,
            "risk_percent": 1.0,
            "is_crisis": true,
            "vsa_confirmed": false,
            "veto": ""
        }
    }
}